README.md
setup.cfg
setup.py
myvr/__init__.py
myvr/client.py
myvr/api/__init__.py
myvr/api/exceptions.py
myvr/api/mixins.py
myvr/api/myvr_objects.py
myvr/api/resource.py
myvr/resources/__init__.py
myvr/resources/accounts/__init__.py
myvr/resources/accounts/account.py
myvr/resources/accounts/user.py
myvr/resources/bookings/__init__.py
myvr/resources/bookings/cancellation_reason.py
myvr/resources/bookings/expense.py
myvr/resources/bookings/payment.py
myvr/resources/bookings/payment_method.py
myvr/resources/bookings/promotion.py
myvr/resources/bookings/quote.py
myvr/resources/bookings/refund.py
myvr/resources/bookings/reservation.py
myvr/resources/channels/__init__.py
myvr/resources/channels/channel_account.py
myvr/resources/channels/channel_listing.py
myvr/resources/crm/__init__.py
myvr/resources/crm/contact.py
myvr/resources/crm/contact_address.py
myvr/resources/crm/contact_email.py
myvr/resources/crm/contact_note.py
myvr/resources/crm/contact_phone.py
myvr/resources/crm/contact_tag.py
myvr/resources/crm/inquiry.py
myvr/resources/crm/inquiry_message.py
myvr/resources/crm/message_template.py
myvr/resources/crm/source.py
myvr/resources/crm/tag.py
myvr/resources/pricing/__init__.py
myvr/resources/pricing/fee.py
myvr/resources/pricing/fee_plan.py
myvr/resources/pricing/rate.py
myvr/resources/pricing/rate_plan.py
myvr/resources/properties/__init__.py
myvr/resources/properties/amenity.py
myvr/resources/properties/calendar_event.py
myvr/resources/properties/daily_availability.py
myvr/resources/properties/photo.py
myvr/resources/properties/property.py
myvr/resources/properties/property_hierarchy.py
myvr/resources/properties/room.py
myvr/resources/property_groups/__init__.py
myvr/resources/property_groups/group.py
myvr/resources/property_groups/membership.py
myvr/resources/settings/__init__.py
myvr/resources/settings/custom_field.py
myvr/resources/settings/merchant_account.py
myvr_python.egg-info/PKG-INFO
myvr_python.egg-info/SOURCES.txt
myvr_python.egg-info/dependency_links.txt
myvr_python.egg-info/requires.txt
myvr_python.egg-info/top_level.txt