Metadata-Version: 2.1
Name: myvr-python
Version: 0.0.4
Summary: Python wrapper for MyVR API
Home-page: https://github.com/myvr/myvr-python
Author: MyVR
License: GNU
Download-URL: https://github.com/myvr/myvr-python/archive/0.0.3.tar.gz
Platform: UNKNOWN
Classifier: Development Status :: 4 - Beta
Classifier: Programming Language :: Python :: 3.7
Classifier: Programming Language :: Python :: 3.8
Classifier: Programming Language :: Python :: 3.9
Classifier: License :: OSI Approved :: GNU General Public License v3 (GPLv3)
Classifier: Operating System :: OS Independent
Requires-Python: >=3.7, <4
